graphette/__init__.py
graphette/algo.py
graphette/models.py
graphette/visualize.py
graphette-0.1.1.dist-info/METADATA
graphette-0.1.1.dist-info/WHEEL
graphette-0.1.1.dist-info/licenses/LICENSE
graphette-0.1.1.dist-info/RECORD
