Metadata-Version: 2.4
Name: graphette
Version: 0.1.1
Summary: Step-by-step graph algorithm visualization with NetworkX and Matplotlib
Project-URL: Homepage, https://github.com/pzarczynski/graphette
Project-URL: Documentation, https://github.com/pzarczynski/graphette#readme
Project-URL: Repository, https://github.com/pzarczynski/graphette.git
Project-URL: Issues, https://github.com/pzarczynski/graphette/issues
Author-email: Piotr Żarczyński <piotr.zarczynski.06@gmail.com>
License: MIT
License-File: LICENSE
Keywords: algorithm,graph,matplotlib,networkx,visualization
Classifier: Development Status :: 3 - Alpha
Classifier: Intended Audience :: Developers
Classifier: Intended Audience :: Education
Classifier: License :: OSI Approved :: MIT License
Classifier: Programming Language :: Python :: 3
Classifier: Programming Language :: Python :: 3.10
Classifier: Programming Language :: Python :: 3.11
Classifier: Programming Language :: Python :: 3.12
Classifier: Programming Language :: Python :: 3.13
Classifier: Topic :: Scientific/Engineering :: Visualization
Classifier: Topic :: Software Development :: Libraries :: Python Modules
Requires-Python: >=3.10
Requires-Dist: matplotlib>=3.5.0
Requires-Dist: networkx>=3.0
Requires-Dist: toolz>=0.10.0
Provides-Extra: dev
Requires-Dist: ruff>=0.1.0; extra == 'dev'
